{
    "schema_version": "1.2",
    "packages": [
        {
            "name": "Code Alignment",
            "description": "This plugin implements an interface from ST2 to CodeAlignment for VS and Notepad++",
            "author": "Nicholas Buse (@NicholasBuse)",
            "homepage": "http://www.codealignment.com/",
            "last_modified": "2012-03-21 12:00:00",
            "platforms": {
                "windows": [
                    {
                        "version": "1.0.0",
                        "url": "https://github.com/NicholasBuse/sublime_CodeAlignment/raw/master/v1.0.0/CodeAlignment.sublime-package"
                    }
                ]
            }
        }
    ]
}